aafigure_directive.py
setup-docutils-plugin.py
docutils_aafigure.egg-info/PKG-INFO
docutils_aafigure.egg-info/SOURCES.txt
docutils_aafigure.egg-info/dependency_links.txt
docutils_aafigure.egg-info/entry_points.txt
docutils_aafigure.egg-info/requires.txt
docutils_aafigure.egg-info/top_level.txt